xe2/__init__.py
xe2/genenv.py
xe2/generator.py
xe2/inoutstream.py
xe2/main.py
xe2/menu.py
xe2/page.py
xe2/renderer.py
xe2/resource.py
xe2/version.py
xe2/website.py
xe2/templates/website_conf.yml.j2
xe2-2.0.29.dist-info/LICENSE.md
xe2-2.0.29.dist-info/METADATA
xe2-2.0.29.dist-info/WHEEL
xe2-2.0.29.dist-info/entry_points.txt
xe2-2.0.29.dist-info/top_level.txt
xe2-2.0.29.dist-info/RECORD
