Metadata-Version: 2.1
Name: xe2
Version: 2.0.29
Summary: UNKNOWN
Home-page: https://gitlab.com/guichet-entreprises.fr/tools/xenon2
Author: Florent Tournois
Author-email: florent.tournois@gmail.fr
License: MIT
Platform: UNKNOWN
Classifier: Programming Language :: Python
Classifier: Operating System :: OS Independent
Classifier: Programming Language :: Python :: 3
Classifier: Programming Language :: Python :: 3.6
Requires-Dist: pymdtools
Requires-Dist: pyyaml
Requires-Dist: beautifulsoup4
Requires-Dist: jinja2
Requires-Dist: html5lib
Requires-Dist: md2py
Requires-Dist: networkx
Requires-Dist: htmlmin
Requires-Dist: xe2layout
Requires-Dist: python-gitlab
